truecolor.py
truecolor-1.0b2.dist-info/DESCRIPTION.rst
truecolor-1.0b2.dist-info/LICENSE.txt
truecolor-1.0b2.dist-info/METADATA
truecolor-1.0b2.dist-info/RECORD
truecolor-1.0b2.dist-info/WHEEL
truecolor-1.0b2.dist-info/entry_points.txt
truecolor-1.0b2.dist-info/metadata.json
truecolor-1.0b2.dist-info/top_level.txt
