Metadata-Version: 2.0
Name: truecolor
Version: 1.0b2
Summary: A Truecolor terminal library for Python
Home-page: https://github.com/simplegadget512/Truecolor
Author: Albert Freeman
Author-email: simplegadget512@gmail.com
License: MIT
Keywords: ansi color console terminal
Platform: UNKNOWN
Classifier: Environment :: Console
Classifier: Development Status :: 4 - Beta
Classifier: Intended Audience :: Developers
Classifier: License :: OSI Approved :: MIT License
Classifier: Operating System :: OS Independent
Classifier: Programming Language :: Python :: 2
Classifier: Programming Language :: Python :: 3
Classifier: Topic :: Terminals :: Terminal Emulators/X Terminals
Requires-Python: >=2.7
